{"last_tab":"","layout_set":"2","enerzee_layout_image":{"url":"","id":"","height":"","width":"","thumbnail":""},"enerzee_layout_color":"#ffffff","enerzee_back_to_top":"yes","enerzee_fevicon":{"url":"https:\/\/wordpress.iqonic.design\/enerzee\/wp-content\/themes\/enerzee\/assets\/images\/favicon.ico","id":"","height":"","width":"","thumbnail":""},"header_radio":"2","enerzee_logo":{"url":"https:\/\/wordpress.iqonic.design\/enerzee\/wp-content\/themes\/enerzee\/assets\/images\/logo.png","id":"","height":"","width":"","thumbnail":""},"logo-dimensions":{"width":"","height":"","units":"px"},"header_text":"enerzee","header_font":{"font-family":"PT+Sans","font-options":"","google":"1","font-weight":"","font-style":"","subsets":"","font-size":""},"header_logo_color":"#a37cfc","enerzee_display_loader":"yes","loader_color":"#ffffff","enerzee_loader_gif":{"url":"https:\/\/wordpress.iqonic.design\/enerzee\/wp-content\/themes\/enerzee\/assets\/images\/loader.gif","id":"","height":"","width":"","thumbnail":""},"loader-dimensions":{"width":"","height":"","units":"px"},"header_transparent":"2","header_color":"1","header_bg_color":"","header_text_color":"","header_link_color":"","header_link_hover_color":"","header_display_shop":"yes","wishlist_link":"","header_display_button":"yes","enerzee_download_title":"Get Started","enerzee_download_link":"","he_button_color":"1","hedaer_button_color":"","hedaer_button_hover_color":"","hedaer_button_text_color":"","hedaer_button_hover_text_color":"","header_display_search":"yes","enerzee_header_sticky":"2","header_sticky_bg_color":"","header_sticky_bg_color_two":"","bg_image":"1","display_banner":"yes","banner_padding":{"width":"","height":"","units":"px"},"banner_padding_responsive":{"width":"","height":"","units":"px"},"display_breadcrumbs":"yes","display_title":"yes","breadcrumbs_color":"","breadcrumbs_hover_color":"","bg_title_color":"","bg_type":"2","banner_image":{"url":"https:\/\/wordpress.iqonic.design\/enerzee\/wp-content\/uploads\/2020\/02\/01-2.jpg","id":"1606","height":"470","width":"1600","thumbnail":"https:\/\/wordpress.iqonic.design\/enerzee\/wp-content\/uploads\/2020\/02\/01-2-150x150.jpg"},"bg_color":"","bg_video_link":"http:\/\/localhost\/enerzee\/wordpress\/wp-content\/uploads\/2019\/08\/SampleVideo.mp4","bg_opacity":"1","opacity_color":{"color":"","alpha":"1","rgba":""},"enerzee_footer_top_display":"yes","footer_option":"1","footer_type":"1","footer_image":{"url":"http:\/\/localhost\/enerzee\/wordpress\/wp-content\/themes\/enerzee\/assets\/images\/footer-img.jpg","id":"","height":"","width":"","thumbnail":""},"footer_opacity":"1","footer_opacity_color":{"color":"#eff1fe","alpha":"0.9","rgba":"rgba(239,241,254,0.9)"},"footer_color":{"color":"","alpha":"1","rgba":""},"footer_heading_color":"","footer_text_color":"","footer_link_color":"","display_footer":"yes","enerzee_footer_width":"6","footer_one":"1","footer_two":"1","footer_three":"1","footer_fore":"1","display_copyright":"yes","footer_copyright":"Copyright 2023 Enerzee All Rights Reserved.","footer_copy_color":"1","footer_copyright_color":"","enerzee_blog_sidebar":"2","enerzee_blog_type":"1","enerzee_single_blog_sidebar":"0","blog_btn":"Read More","enerzee_blog":"1","enerzee_display_pagination":"yes","enerzee_display_image":"yes","enerzee_display_comment":"yes","enerzee_404_banner_image":{"url":"https:\/\/wordpress.iqonic.design\/enerzee\/wp-content\/themes\/enerzee\/assets\/images\/backend\/404.png","id":"","height":"","width":"","thumbnail":""},"enerzee_fourzerofour_title":"","enerzee_four_description":"Oops! This Page is Not Found.","enerzee_four_description_two":"The requested page does not exist. ","enerzee_fourzerofour_button":"Go Back","enerzee_subscribe":"[mc4wp_form id=\"82\"]","enerzee_subscribe_contant":"It is a long established fact that a page when looking at its layout.","address":"1234 North Avenue Luke Lane, South Bend, IN 360001","phone":"+0123456789","second_phone":"+0123456789","email":"support@iqnonicthemes.com","second_email":"support@iqnonicthemes.com","enerzee_display_social_media":"no","social-media-iq":{"facebook":"","twitter":"","google-plus":"","github":"","instagram":"","linkedin":"","tumblr":"","pinterest":"","dribbble":"","reddit":"","flickr":"","skype":"","youtube-play":"","vimeo":"","soundcloud":"","wechat":"","renren":"","weibo":"","xing":"","qq":"","rss":"","vk":"","behance":"","snapchat":""},"enerzee_change_font":"0","body_font":{"font-family":"Poppins","font-options":"","google":"1","font-weight":"","font-style":"","subsets":"","font-size":""},"primary_menu":{"font-family":"PT+Sans","font-options":"","google":"1","font-weight":"","font-style":"","subsets":"","font-size":""},"sub_menu":{"font-family":"PT+Sans","font-options":"","google":"1","font-weight":"","font-style":"","subsets":"","font-size":""},"h1_font":{"font-family":"PT+Sans","font-options":"","google":"1","font-weight":"","font-style":"","subsets":"","font-size":""},"h2_font":{"font-family":"PT+Sans","font-options":"","google":"1","font-weight":"","font-style":"","subsets":"","font-size":""},"h3_font":{"font-family":"PT+Sans","font-options":"","google":"1","font-weight":"","font-style":"","subsets":"","font-size":""},"h4_font":{"font-family":"PT+Sans","font-options":"","google":"1","font-weight":"","font-style":"","subsets":"","font-size":""},"h5_font":{"font-family":"PT+Sans","font-options":"","google":"1","font-weight":"","font-style":"","subsets":"","font-size":""},"h6_font":{"font-family":"PT+Sans","font-options":"","google":"1","font-weight":"","font-style":"","subsets":"","font-size":""},"page_title_font":{"font-family":"PT+Sans","font-options":"","google":"1","font-weight":"","font-style":"","subsets":"","font-size":""},"page_desc_font":{"font-family":"PT+Sans","font-options":"","google":"1","font-weight":"","font-style":"","subsets":"","font-size":""},"enerzee_color":"1","primary_color":"","secondary_color":"","tertiary_color":"","white_color":"","portfolio_before_color":{"color":"","alpha":"1","rgba":""},"portfolio_after_color":{"color":"","alpha":"1","rgba":""},"list_wrapper_color":{"color":"","alpha":"1","rgba":""},"redux-backup":1}